<ui:UiBinder xmlns:ui='urn:ui:com.google.gwt.uibinder' xmlns:g='urn:import:com.google.gwt.user.client.ui' xmlns:b="urn:import:com.github.gwtbootstrap.client.ui">
	<g:FlowPanel addStyleNames="profilePanel">
		<g:FlowPanel ui:field="profileFields" addStyleNames="profileFields">
		</g:FlowPanel>
		<g:FlowPanel addStyleNames="standardButtonBar">
			<g:Button ui:field="btnOK" addStyleNames="btnAction btnStandard"/>
			<g:Button ui:field="btnCancel" addStyleNames="btnNotSelected btnStandard"/>
		</g:FlowPanel>
	</g:FlowPanel>
</ui:UiBinder>